setup.py
tornado_serial/__init__.py
tornado_serial/serial.py
tornado_serial.egg-info/PKG-INFO
tornado_serial.egg-info/SOURCES.txt
tornado_serial.egg-info/dependency_links.txt
tornado_serial.egg-info/requires.txt
tornado_serial.egg-info/top_level.txt