Metadata-Version: 1.0
Name: tornado-serial
Version: 0.1.0
Summary: Asynchronous serial port access for python tornado
Home-page: http://github.com/jianingy/tornado_serial/
Author: Jianing Yang
Author-email: jianingy.yang@gmail.com
License: http://www.apache.org/licenses/LICENSE-2.0
Platform: UNKNOWN
